llama_index/readers/faiss/__init__.py
llama_index/readers/faiss/base.py
llama_index_readers_faiss-0.4.0.dist-info/METADATA
llama_index_readers_faiss-0.4.0.dist-info/WHEEL
llama_index_readers_faiss-0.4.0.dist-info/licenses/LICENSE
llama_index_readers_faiss-0.4.0.dist-info/RECORD
